[
  {
    "trend_arrow": "FLAT", 
    "display_time": "2016-10-10T15:59:26-07:00", 
    "noise": 1, 
    "system_time": "2016-10-10T21:53:16-07:00", 
    "direction": "Flat", 
    "sgv": 108, 
    "dateString": "2016-10-10T15:59:26-07:00", 
    "date": 1476140366000, 
    "unfiltered": 126672, 
    "filtered": 129264, 
    "device": "openaps://indy-e1/cgm", 
    "rssi": 206, 
    "type": "sgv", 
    "glucose": 108
  }, 
  {
    "trend_arrow": "45_DOWN", 
    "display_time": "2016-10-10T15:54:26-07:00", 
    "noise": 1, 
    "system_time": "2016-10-10T21:48:16-07:00", 
    "direction": "FortyFiveDown", 
    "sgv": 108, 
    "dateString": "2016-10-10T15:54:26-07:00", 
    "date": 1476140066000, 
    "unfiltered": 126672, 
    "filtered": 135904, 
    "device": "openaps://indy-e1/cgm", 
    "rssi": 196, 
    "type": "sgv", 
    "glucose": 108
  }
]