[
  {
    "trend_arrow": "FLAT", 
    "display_time": "2016-10-13T22:34:17-07:00", 
    "noise": 1, 
    "system_time": "2016-10-14T05:22:24-07:00", 
    "direction": "Flat", 
    "sgv": 107, 
    "dateString": "2016-10-13T22:34:17-07:00", 
    "date": 1476423257000, 
    "unfiltered": 111488, 
    "filtered": 106448, 
    "device": "openaps://indy-e1/cgm", 
    "rssi": 189, 
    "type": "sgv", 
    "glucose": 107
  }, 
  {
    "trend_arrow": "FLAT", 
    "display_time": "2016-10-13T22:29:18-07:00", 
    "noise": 1, 
    "system_time": "2016-10-14T05:17:25-07:00", 
    "direction": "Flat", 
    "sgv": 104, 
    "dateString": "2016-10-13T22:29:18-07:00", 
    "date": 1476422958000, 
    "unfiltered": 109024, 
    "filtered": 101968, 
    "device": "openaps://indy-e1/cgm", 
    "rssi": 434, 
    "type": "sgv", 
    "glucose": 104
  }
]