[
  {
    "trend_arrow": "45_UP", 
    "display_time": "2016-10-10T08:19:27-07:00", 
    "noise": 1, 
    "system_time": "2016-10-10T14:13:17-07:00", 
    "direction": "FortyFiveUp", 
    "sgv": 119, 
    "dateString": "2016-10-10T08:19:27-07:00", 
    "date": 1476112767000, 
    "unfiltered": 137408, 
    "filtered": 128096, 
    "device": "openaps://indy-e1/cgm", 
    "rssi": 206, 
    "type": "sgv", 
    "glucose": 119
  }, 
  {
    "trend_arrow": "FLAT", 
    "display_time": "2016-10-10T08:14:27-07:00", 
    "noise": 1, 
    "system_time": "2016-10-10T14:08:17-07:00", 
    "direction": "Flat", 
    "sgv": 115, 
    "dateString": "2016-10-10T08:14:27-07:00", 
    "date": 1476112467000, 
    "unfiltered": 133088, 
    "filtered": 123984, 
    "device": "openaps://indy-e1/cgm", 
    "rssi": 213, 
    "type": "sgv", 
    "glucose": 115
  }
]