[
  {
    "trend_arrow": "FLAT", 
    "display_time": "2016-10-12T06:54:21-07:00", 
    "noise": 1, 
    "system_time": "2016-10-12T12:48:10-07:00", 
    "direction": "Flat", 
    "sgv": 85, 
    "dateString": "2016-10-12T06:54:21-07:00", 
    "device": "openaps://indy-e1/cgm", 
    "unfiltered": 89152, 
    "rssi": 190, 
    "date": 1476280461000, 
    "filtered": 90864, 
    "type": "sgv", 
    "glucose": 85
  }, 
  {
    "trend_arrow": "FLAT", 
    "display_time": "2016-10-12T06:49:21-07:00", 
    "noise": 1, 
    "system_time": "2016-10-12T12:43:10-07:00", 
    "direction": "Flat", 
    "sgv": 86, 
    "dateString": "2016-10-12T06:49:21-07:00", 
    "device": "openaps://indy-e1/cgm", 
    "unfiltered": 90800, 
    "rssi": 175, 
    "date": 1476280161000, 
    "filtered": 93472, 
    "type": "sgv", 
    "glucose": 86
  }
]