[
  {
    "trend_arrow": "45_UP", 
    "display_time": "2016-10-14T18:19:14-07:00", 
    "noise": 1, 
    "direction": "FortyFiveUp", 
    "system_time": "2016-10-15T01:07:20-07:00", 
    "sgv": 127, 
    "dateString": "2016-10-14T18:19:14-07:00", 
    "device": "openaps://indy-e1/cgm", 
    "unfiltered": 129184, 
    "rssi": 437, 
    "date": 1476494354000.0, 
    "filtered": 118336, 
    "type": "sgv", 
    "glucose": 127
  }, 
  {
    "trend_arrow": "SINGLE_UP", 
    "display_time": "2016-10-14T18:14:13-07:00", 
    "noise": 1, 
    "direction": "SingleUp", 
    "system_time": "2016-10-15T01:02:20-07:00", 
    "sgv": 120, 
    "dateString": "2016-10-14T18:14:13-07:00", 
    "device": "openaps://indy-e1/cgm", 
    "unfiltered": 123216, 
    "rssi": 193, 
    "date": 1476494053000.0, 
    "filtered": 107296, 
    "type": "sgv", 
    "glucose": 120
  }, 
  {
    "trend_arrow": "SINGLE_UP", 
    "display_time": "2016-10-14T18:09:13-07:00", 
    "noise": 1, 
    "direction": "SingleUp", 
    "system_time": "2016-10-15T00:57:20-07:00", 
    "sgv": 113, 
    "dateString": "2016-10-14T18:09:13-07:00", 
    "device": "openaps://indy-e1/cgm", 
    "unfiltered": 116592, 
    "rssi": 185, 
    "date": 1476493753000.0, 
    "filtered": 96464, 
    "type": "sgv", 
    "glucose": 113
  }, 
  {
    "trend_arrow": "45_UP", 
    "display_time": "2016-10-14T18:04:13-07:00", 
    "noise": 1, 
    "direction": "FortyFiveUp", 
    "system_time": "2016-10-15T00:52:20-07:00", 
    "sgv": 98, 
    "dateString": "2016-10-14T18:04:13-07:00", 
    "device": "openaps://indy-e1/cgm", 
    "unfiltered": 103008, 
    "rssi": 186, 
    "date": 1476493453000.0, 
    "filtered": 88128, 
    "type": "sgv", 
    "glucose": 98
  }, 
  {
    "trend_arrow": "FLAT", 
    "display_time": "2016-10-14T17:59:13-07:00", 
    "noise": 1, 
    "direction": "Flat", 
    "system_time": "2016-10-15T00:47:20-07:00", 
    "sgv": 85, 
    "dateString": "2016-10-14T17:59:13-07:00", 
    "device": "openaps://indy-e1/cgm", 
    "unfiltered": 91312, 
    "rssi": 182, 
    "date": 1476493153000.0, 
    "filtered": 82960, 
    "type": "sgv", 
    "glucose": 85
  }, 
  {
    "trend_arrow": "FLAT", 
    "display_time": "2016-10-14T17:54:13-07:00", 
    "noise": 1, 
    "direction": "Flat", 
    "system_time": "2016-10-15T00:42:20-07:00", 
    "sgv": 78, 
    "dateString": "2016-10-14T17:54:13-07:00", 
    "device": "openaps://indy-e1/cgm", 
    "unfiltered": 84944, 
    "rssi": 175, 
    "date": 1476492853000.0, 
    "filtered": 80112, 
    "type": "sgv", 
    "glucose": 78
  }
]