[
  {
    "trend_arrow": "FLAT", 
    "display_time": "2016-10-15T13:19:09-07:00", 
    "noise": 1, 
    "system_time": "2016-10-15T20:07:16-07:00", 
    "direction": "Flat", 
    "sgv": 97, 
    "dateString": "2016-10-15T13:19:09-07:00", 
    "device": "openaps://indy-e1/cgm", 
    "unfiltered": 100320, 
    "rssi": 186, 
    "date": 1476562749000, 
    "filtered": 107088, 
    "type": "sgv", 
    "glucose": 97
  }, 
  {
    "trend_arrow": "FLAT", 
    "display_time": "2016-10-15T13:14:09-07:00", 
    "noise": 1, 
    "system_time": "2016-10-15T20:02:16-07:00", 
    "direction": "Flat", 
    "sgv": 103, 
    "dateString": "2016-10-15T13:14:09-07:00", 
    "device": "openaps://indy-e1/cgm", 
    "unfiltered": 106080, 
    "rssi": 183, 
    "date": 1476562449000, 
    "filtered": 110544, 
    "type": "sgv", 
    "glucose": 103
  }
]