[
  {
    "trend_arrow": "FLAT", 
    "display_time": "2016-10-12T02:24:22-07:00", 
    "noise": 1, 
    "system_time": "2016-10-12T08:18:12-07:00", 
    "direction": "Flat", 
    "sgv": 138, 
    "dateString": "2016-10-12T02:24:22-07:00", 
    "device": "openaps://indy-e1/cgm", 
    "unfiltered": 151520, 
    "rssi": 434, 
    "date": 1476264262000, 
    "filtered": 155008, 
    "type": "sgv", 
    "glucose": 138
  }, 
  {
    "trend_arrow": "45_DOWN", 
    "display_time": "2016-10-12T02:19:21-07:00", 
    "noise": 1, 
    "system_time": "2016-10-12T08:13:11-07:00", 
    "direction": "FortyFiveDown", 
    "sgv": 138, 
    "dateString": "2016-10-12T02:19:21-07:00", 
    "device": "openaps://indy-e1/cgm", 
    "unfiltered": 151328, 
    "rssi": 179, 
    "date": 1476263961000, 
    "filtered": 159872, 
    "type": "sgv", 
    "glucose": 138
  }
]