[
  {
    "trend_arrow": "FLAT", 
    "display_time": "2016-10-13T20:24:18-07:00", 
    "noise": 1, 
    "direction": "Flat", 
    "system_time": "2016-10-14T03:12:24-07:00", 
    "sgv": 110, 
    "dateString": "2016-10-13T20:24:18-07:00", 
    "device": "openaps://indy-e1/cgm", 
    "unfiltered": 114928, 
    "rssi": 192, 
    "date": 1476415458000.0, 
    "filtered": 119376, 
    "type": "sgv", 
    "glucose": 110
  }, 
  {
    "trend_arrow": "FLAT", 
    "display_time": "2016-10-13T20:19:18-07:00", 
    "noise": 1, 
    "direction": "Flat", 
    "system_time": "2016-10-14T03:07:24-07:00", 
    "sgv": 116, 
    "dateString": "2016-10-13T20:19:18-07:00", 
    "device": "openaps://indy-e1/cgm", 
    "unfiltered": 119968, 
    "rssi": 198, 
    "date": 1476415158000.0, 
    "filtered": 119360, 
    "type": "sgv", 
    "glucose": 116
  }, 
  {
    "trend_arrow": "FLAT", 
    "display_time": "2016-10-13T20:14:18-07:00", 
    "noise": 1, 
    "direction": "Flat", 
    "system_time": "2016-10-14T03:02:25-07:00", 
    "sgv": 117, 
    "dateString": "2016-10-13T20:14:18-07:00", 
    "device": "openaps://indy-e1/cgm", 
    "unfiltered": 120720, 
    "rssi": 444, 
    "date": 1476414858000.0, 
    "filtered": 118784, 
    "type": "sgv", 
    "glucose": 117
  }, 
  {
    "trend_arrow": "FLAT", 
    "display_time": "2016-10-13T20:09:18-07:00", 
    "noise": 1, 
    "direction": "Flat", 
    "system_time": "2016-10-14T02:57:25-07:00", 
    "sgv": 114, 
    "dateString": "2016-10-13T20:09:18-07:00", 
    "device": "openaps://indy-e1/cgm", 
    "unfiltered": 118576, 
    "rssi": 207, 
    "date": 1476414558000.0, 
    "filtered": 118464, 
    "type": "sgv", 
    "glucose": 114
  }, 
  {
    "trend_arrow": "FLAT", 
    "display_time": "2016-10-13T20:04:18-07:00", 
    "noise": 1, 
    "direction": "Flat", 
    "system_time": "2016-10-14T02:52:24-07:00", 
    "sgv": 114, 
    "dateString": "2016-10-13T20:04:18-07:00", 
    "device": "openaps://indy-e1/cgm", 
    "unfiltered": 118640, 
    "rssi": 220, 
    "date": 1476414258000.0, 
    "filtered": 118464, 
    "type": "sgv", 
    "glucose": 114
  }, 
  {
    "trend_arrow": "FLAT", 
    "display_time": "2016-10-13T19:59:18-07:00", 
    "noise": 1, 
    "direction": "Flat", 
    "system_time": "2016-10-14T02:47:24-07:00", 
    "sgv": 115, 
    "dateString": "2016-10-13T19:59:18-07:00", 
    "device": "openaps://indy-e1/cgm", 
    "unfiltered": 118944, 
    "rssi": 209, 
    "date": 1476413958000.0, 
    "filtered": 118240, 
    "type": "sgv", 
    "glucose": 115
  }
]